zuz/__init__.py
zuz/datasets.py
zuz/resources/woof-DALL-E.01.png
zuz/resources/woof-DALL-E.02.png
zuz-0.0.1.dist-info/METADATA
zuz-0.0.1.dist-info/WHEEL
zuz-0.0.1.dist-info/top_level.txt
zuz-0.0.1.dist-info/RECORD
